{"season":"2010-spring","count":93,"items":[{"id":244,"title":"Angel Beats!","image":null,"officialSiteUrl":"https://www.angelbeats.jp/","watchers":14396,"services":[],"otherServices":[],"hasBroadcastData":true,"broadcastStartDate":null,"broadcastWeekday":null,"broadcastTime":null,"creditNames":["喜多村英梨","神谷浩史","木村良平","水島大宙","高木俊","村上正博","高橋歩","山崎嘉雅","井上佳津枝","宮下雄次、川面恒介","平田雄三","飯田里樹","ビジュアルアーツ、1st PLACE","佐藤勝史","麻枝准","ANANT-GARDE EYES、麻枝准","東地和生","Na-Ga","岸誠二","Angel Beats! Project(アニプレックス、アスキー・メディアワークス、ビジュアルアーツ、P.A.WORKS、ムービック、電通、毎日放送)、中部日本放送"],"castNames":["喜多村英梨","神谷浩史","木村良平","水島大宙","高木俊"],"media":"TV"},{"id":669,"title":"けいおん！！","image":"http://www.tbs.co.jp/anime/k-on/images/logo.jpg","officialSiteUrl":"https://www.tbs.co.jp/anime/k-on/","watchers":13700,"services":[],"otherServices":[],"hasBroadcastData":true,"broadcastStartDate":null,"broadcastWeekday":null,"broadcastTime":null,"creditNames":["真田アサミ","豊崎愛生","藤東知夏","米澤円","永田依子","高橋博行","山本倫","竹田明代","田村せいき","吉田玲子","かきふらい","重村建吾","京都アニメーション","百石元","堀口悠紀子","鶴岡陽太","山田尚子","小森茂生","桜高軽音部","TBS"],"castNames":["真田アサミ","豊崎愛生","藤東知夏","米澤円","永田依子"],"media":"TV"},{"id":2459,"title":"WORKING!!","image":"http://www.wagnaria.com/assets/img/ogp.jpg","officialSiteUrl":"https://www.wagnaria.com/","watchers":9465,"services":[],"otherServices":[],"hasBroadcastData":false,"broadcastStartDate":null,"broadcastWeekday":null,"broadcastTime":null,"creditNames":["阿澄佳奈","渡辺久美子","小野大輔","神谷浩史","広橋涼","MONACA","足立慎吾","平池芳正","ヤングガンガン(スクウェア・エニックス)","田尻健一","高津カリノ","鶴岡陽太","廣岡岳","A-1 Pictures","「WORKING!!」製作委員会(アニプレックス、読売テレビ)","楽音舎","坂本いづみ","明珍宇作","坪根健太郎"],"castNames":["阿澄佳奈","渡辺久美子","小野大輔","神谷浩史","広橋涼"],"media":"TV"},{"id":2321,"title":"四畳半神話大系","image":null,"officialSiteUrl":"http://yojouhan.noitamina.tv/","watchers":5466,"services":[],"otherServices":[],"hasBroadcastData":true,"broadcastStartDate":null,"broadcastWeekday":null,"broadcastTime":null,"creditNames":["藤原啓治","大原さやか","浅沼晋太郎","吉野裕行","甲斐田裕子","石塚恵子","辻田邦夫","伊東伸高","上田誠","大島ミチル","木村絵理子","上原伸一","中村佑介","湯浅政明","森見登美彦","マッドハウス","木村佳史子"],"castNames":["藤原啓治","大原さやか","浅沼晋太郎","吉野裕行","甲斐田裕子"],"media":"TV"},{"id":108,"title":"荒川アンダー ザ ブリッジ","image":null,"officialSiteUrl":"http://www.tv-tokyo.co.jp/anime/arakawa_ub/","watchers":4761,"services":[],"otherServices":[],"hasBroadcastData":false,"broadcastStartDate":null,"broadcastWeekday":null,"broadcastTime":null,"creditNames":["坂本真綾","藤原啓治","杉田智和","子安武人","大塚芳忠","中村光","田口浩司","森山敦","北村敦","倉重宣之","佐藤エミ","宿利剛","久保田光俊","杉山延寛","宮本幸裕","東厚治","滝沢いづみ","酒井基","内村祥平"],"castNames":["坂本真綾","藤原啓治","杉田智和","子安武人","大塚芳忠"],"media":"TV"},{"id":3726,"title":"名探偵コナン 天空の難破船","image":"https://www.tms-e.co.jp/media/001/202102/ogimage.png","officialSiteUrl":"http://www.tms-e.co.jp/search/introduction.php?pdt_no=366","watchers":3430,"services":[],"otherServices":[],"hasBroadcastData":false,"broadcastStartDate":null,"broadcastWeekday":null,"broadcastTime":null,"creditNames":["東京ムービー","トムス・エンタテインメント"],"castNames":[],"media":"MOVIE"},{"id":2087,"title":"迷い猫オーバーラン！","image":null,"officialSiteUrl":null,"watchers":3234,"services":[],"otherServices":[],"hasBroadcastData":true,"broadcastStartDate":null,"broadcastWeekday":null,"broadcastTime":null,"creditNames":["田村ゆかり","吉野裕行","佐藤利奈","佐藤聡美","堀江由衣","迷い猫同好会","廣瀬清志","石黒晴嗣","鈴木寿枝","木村暢","ぺこ","高木隆次","前田実","池端隆史","AIC","佐藤卓哉","佐藤順一","板垣伸","福田道生","中本尚"],"castNames":["田村ゆかり","吉野裕行","佐藤利奈","佐藤聡美","堀江由衣"],"media":"TV"},{"id":487,"title":"kiss×sis","image":null,"officialSiteUrl":null,"watchers":2903,"services":[],"otherServices":[],"hasBroadcastData":false,"broadcastStartDate":null,"broadcastWeekday":null,"broadcastTime":null,"creditNames":["武内健","永田依子","今井麻美","大亀あすか","巽悠衣子","kiss×sis製作委員会","ガンジス","瀧ヶ崎誠","スタジオごんぐ","楽音舎","高宮城梨江","森山敦","月刊ヤングマガジン(講談社)","植木瑞基 in 俊龍","菊田浩巳","小坂部直子","下谷智之","長谷川勝己","名和宗則","ぢたま某"],"castNames":["武内健","永田依子","今井麻美","大亀あすか","巽悠衣子"],"media":"TV"},{"id":3232,"title":"劇場版 銀魂 新訳紅桜篇","image":"http://wwws.warnerbros.co.jp/gintama/social_thumb.png","officialSiteUrl":"http://wwws.warnerbros.co.jp/gintama/sp/index.php#top","watchers":2552,"services":[],"otherServices":[],"hasBroadcastData":false,"broadcastStartDate":null,"broadcastWeekday":null,"broadcastTime":null,"creditNames":["杉田智和","阪口大助","雪野五月","石田彰","千葉進歩","空知英秋「銀魂」","高松信司","藤田陽一","竹内進二","大和屋暁","サンライズ"],"castNames":["杉田智和","阪口大助","雪野五月","石田彰","千葉進歩"],"media":"MOVIE"},{"id":3615,"title":"東のエデン 劇場版Ⅱ Paradise Lost","image":null,"officialSiteUrl":"http://juiz.jp/special/","watchers":2396,"services":[],"otherServices":[],"hasBroadcastData":false,"broadcastStartDate":null,"broadcastWeekday":null,"broadcastTime":null,"creditNames":["森田成一","木村良平","川原元幸","斉藤貴美子","田谷隼","田中宏侍","山本幸治","神山健治","吉原正行","羽海野チカ","森川聡子","中村悟","竹田悠介","若林和弘","片山由美子","遠藤誠","川井憲次","Production I.G","石井朋彦","アスミック・エース"],"castNames":["森田成一","木村良平","川原元幸","斉藤貴美子","田谷隼"],"media":"MOVIE"},{"id":429,"title":"会長はメイド様！","image":null,"officialSiteUrl":"http://www.tbs.co.jp/anime/maidsama/","watchers":2147,"services":[],"otherServices":[],"hasBroadcastData":true,"broadcastStartDate":null,"broadcastWeekday":null,"broadcastTime":null,"creditNames":["小林ゆう","藤村歩","椎橋和義","市来光弘","鳥海浩輔","黒澤豊","石田美由紀","月刊LaLa(白泉社)","前口渉","後藤正浩","本山哲","J.C.STAFF","ジェネオン・ユニバーサル・エンターテイメント、白泉社、ムービック、J.C.STAFF","メイド様！プロジェクト、TBS","井本由紀","池田眞美子","桜井弘明","藤原ヒロ","小林七郎"],"castNames":["小林ゆう","藤村歩","椎橋和義","市来光弘","鳥海浩輔"],"media":"TV"},{"id":3146,"title":"イヴの時間 劇場版","image":null,"officialSiteUrl":"http://timeofeve.com/","watchers":2122,"services":[],"otherServices":[],"hasBroadcastData":false,"broadcastStartDate":null,"broadcastWeekday":null,"broadcastTime":null,"creditNames":["野島健児","杉田智和","田中理恵","福山潤","佐藤利奈","スタジオ六花","長江努","真家祐也、安部勇士、池部博也","古谷正志、立花康夫、青木正俊","大久保和美","Wish","Code、Wish","大谷久美子","井上あきこ","木霊、ホッチカズヒロ、増山修","小野修、松本泰史","長谷川拓哉","安藤伸幸、安喰秀一","茶山隆介","岡田徹"],"castNames":["野島健児","杉田智和","田中理恵","福山潤","佐藤利奈"],"media":"MOVIE"},{"id":1751,"title":"B型H系","image":null,"officialSiteUrl":null,"watchers":1507,"services":[],"otherServices":[],"hasBroadcastData":false,"broadcastStartDate":null,"broadcastWeekday":null,"broadcastTime":null,"creditNames":["小林ゆう","花澤香菜","能登麻美子","阿部敦","田村ゆかり","ハルフィルムメーカー","長牛豊","渋谷一彦","中村嘉博","阿部智之","ミキミチヨ","西園悟","さんりようこ","ふでやすかずゆき","明瀬礼洋","与口奈津江","Elements Garden","八尋裕子","週刊ヤングジャンプ"],"castNames":["小林ゆう","花澤香菜","能登麻美子","阿部敦","田村ゆかり"],"media":"TV"},{"id":2196,"title":"MAJOR 第6シリーズ","image":"http://www6.nhk.or.jp/anime/program/common/images/major6/og_image.jpg","officialSiteUrl":"http://www6.nhk.or.jp/anime/program/detail.html?i=major6","watchers":1445,"services":[],"otherServices":[],"hasBroadcastData":true,"broadcastStartDate":null,"broadcastWeekday":null,"broadcastTime":null,"creditNames":["森久保祥太郎","川上貴史","森川智之","家中宏","石井康嗣","佐藤太朗","立中順平","大貫健一","斎藤隆","中川幸太郎","飯塚康一","佐野秀典","土屋理敬","NHK、小学館集英社プロダクション","満田拓也","福島利規","Synergy SP"],"castNames":["森久保祥太郎","川上貴史","森川智之","家中宏","石井康嗣"],"media":"TV"},{"id":134,"title":"いちばんうしろの大魔王","image":null,"officialSiteUrl":"https://www.marv.jp/special/daimao/","watchers":1334,"services":[],"otherServices":[],"hasBroadcastData":false,"broadcastStartDate":null,"broadcastWeekday":null,"broadcastTime":null,"creditNames":["近藤隆","代永翼","伊藤静","広橋涼","たかはし智秋","GENCO","アートランド","コンスタン魔術学院(マーベラスエンターテイメント、メディアファクトリー、ホビージャパン、AT-X、グッドスマイルカンパニー、GENCO、ランティス)","デルファイサウンド","宮武一貴","大西博","吉岡たかを","河合伸治","伊藤宗一","赤星政尚","渡部高志","水城正太郎(HJ文庫)","本山哲","小林利充","小関雅"],"castNames":["近藤隆","代永翼","伊藤静","広橋涼","たかはし智秋"],"media":"TV"},{"id":290,"title":"おおきく振りかぶって～夏の大会編～","image":null,"officialSiteUrl":"https://www.oofuri.com/2nd/index.html","watchers":1168,"services":[],"otherServices":[],"hasBroadcastData":false,"broadcastStartDate":null,"broadcastWeekday":null,"broadcastTime":null,"creditNames":["代永翼","谷山紀章","下野紘","佐藤雄大","鈴木千尋","おお振り製作委員会(アニプレックス、A-1 Pictures、TBS、講談社、ムービック、毎日放送)","谷口淳一郎","浜口史郎","菊田浩巳","吉田隆彦","黒田洋介","水島努","ひぐちアサ「おおきく振りかぶって」","高田晃、谷口淳一郎","月刊アフタヌーン(講談社)","A-1 Pictures"],"castNames":["代永翼","谷山紀章","下野紘","佐藤雄大","鈴木千尋"],"media":"TV"},{"id":3271,"title":"クレヨンしんちゃん 超時空！嵐を呼ぶオラの花嫁","image":null,"officialSiteUrl":null,"watchers":1098,"services":[],"otherServices":[],"hasBroadcastData":false,"broadcastStartDate":null,"broadcastWeekday":null,"broadcastTime":null,"creditNames":["シンエイ動画"],"castNames":[],"media":"MOVIE"},{"id":2027,"title":"まじっく快斗","image":null,"officialSiteUrl":null,"watchers":1008,"services":[],"otherServices":[],"hasBroadcastData":false,"broadcastStartDate":null,"broadcastWeekday":null,"broadcastTime":null,"creditNames":["山口勝平","藤村歩","石塚運昇","矢田耕冶","池田秀一","柳田美和","久恒直樹","宮下隼一","梅堀淳","長崎行男","植田秀蔵","佐藤正樹","平野俊貴","青山剛昌","トムス・エンタテインメント"],"castNames":["山口勝平","藤村歩","石塚運昇","矢田耕冶","池田秀一"],"media":"TV"},{"id":1735,"title":"薄桜鬼","image":null,"officialSiteUrl":"http://www.nbcuni.co.jp/rondorobe/anime/hakuoki/tv/","watchers":996,"services":[],"otherServices":[],"hasBroadcastData":false,"broadcastStartDate":null,"broadcastWeekday":null,"broadcastTime":null,"creditNames":["森久保祥太郎","鳥海浩輔","吉野裕行","遊佐浩二","大川透","下崎昭","松本真司","藤澤経清","大谷幸","岩浪美和","平柳悟","中嶋敦子","カズキヨネ","ヤマサキオサム","オトメイト(アイデアファクトリー、デザインファクトリー)","「薄桜鬼」製作委員会(ジェネオン・ユニバーサル・エンターテイメント、フロンティアワークス、AT-X)","松村正宏","スタジオディーン"],"castNames":["森久保祥太郎","鳥海浩輔","吉野裕行","遊佐浩二","大川透"],"media":"TV"},{"id":857,"title":"GIANT KILLING","image":null,"officialSiteUrl":"https://www6.nhk.or.jp/anime/program/detail.html?i=giantkilling","watchers":632,"services":[],"otherServices":[],"hasBroadcastData":false,"broadcastStartDate":null,"broadcastWeekday":null,"broadcastTime":null,"creditNames":["水島大宙","小野大輔","伊藤健太郎","桐井大介","中田隼人","森英治","NHK","廣岡篤哉、柴田裕司","浦崎宣光","北爪英子","モーニング(講談社)","綱本将也","高橋剛","東潤一","熊谷哲矢","川瀬敏文","紅優","ツジトモ","松村正宏","近藤慎与"],"castNames":["水島大宙","小野大輔","伊藤健太郎","桐井大介","中田隼人"],"media":"TV"},{"id":3010,"title":"xxxHOLiC・籠","image":null,"officialSiteUrl":"http://gentei.kodansha.co.jp/content/tsubaholi/rou/","watchers":492,"services":[],"otherServices":[],"hasBroadcastData":false,"broadcastStartDate":null,"broadcastWeekday":null,"broadcastTime":null,"creditNames":["Production I.G","CLAMP"],"castNames":[],"media":"OVA"},{"id":5743,"title":"ケムリクサ","image":null,"officialSiteUrl":null,"watchers":436,"services":[],"otherServices":[],"hasBroadcastData":false,"broadcastStartDate":null,"broadcastWeekday":null,"broadcastTime":null,"creditNames":["たつき","平安","タチ","ゆっこ","ちゃぼ","かきね","irodori"],"castNames":[],"media":"WEB"},{"id":981,"title":"真・恋姫†無双～乙女大乱～","image":null,"officialSiteUrl":null,"watchers":426,"services":[],"otherServices":[],"hasBroadcastData":true,"broadcastStartDate":null,"broadcastWeekday":null,"broadcastTime":null,"creditNames":["MARIO","水橋かおり","いのくちゆか","萩原えみこ","結本ミチル","真恋姫無双製作委員会(マーベラスエンターテイメント、ポニーキャニオン、AT-X)","木尾栄子、斎藤裕二","高畑裕一郎","中野勝博","デルファイサウンド","田村ゆり","伊藤邦彦","石黒けい","平塚知哉","大島美和","多田彰文","ハマノカズゾウ","スタジオ・ライブ","雑破業","真・恋姫†無双～乙女繚乱☆三国志演義～"],"castNames":["MARIO","水橋かおり","いのくちゆか","萩原えみこ","結本ミチル"],"media":"TV"},{"id":3635,"title":"劇場版 \"文学少女\"","image":null,"officialSiteUrl":null,"watchers":418,"services":[],"otherServices":[],"hasBroadcastData":false,"broadcastStartDate":null,"broadcastWeekday":null,"broadcastTime":null,"creditNames":["水樹奈々","宮野真守","小野大輔","下田麻美","平野綾","野村美月「“文学少女”シリーズ」(ファミ通文庫)","多田俊介","山田由香","竹岡美穂","黄瀬和哉、奥田陽介、吉田優子、関口可奈味、手塚響平、佐野恵一","鈴木路恵","中嶋聡彦","伊藤真澄","松本圭太","太田恵子","塩澤良憲、藤瀬智康","津守裕子","田中宏侍","植松淳一","三間雅文"],"castNames":["水樹奈々","宮野真守","小野大輔","下田麻美","平野綾"],"media":"MOVIE"},{"id":1145,"title":"閃光のナイトレイド","image":null,"officialSiteUrl":"http://www.1931.tv/","watchers":401,"services":[],"otherServices":[],"hasBroadcastData":false,"broadcastStartDate":null,"broadcastWeekday":null,"broadcastTime":null,"creditNames":["吉野裕行","生田善子","星野貴紀","平田広明","宮内敦士","常木志伸","那須信司","葉加瀬太郎","山田稔","谷岡善王","佐々木啓悟","上条明峰","松本淳","中島和子","ヤマトナオミチ","金平和茂","大西信介","閃光のナイトレイド製作委員会(アニプレックス、テレビ東京)","A-1 Pictures"],"castNames":["吉野裕行","生田善子","星野貴紀","平田広明","宮内敦士"],"media":"TV"},{"id":3631,"title":"映画プリキュアオールスターズDX2 希望の光☆レインボージュエルを守れ！","image":null,"officialSiteUrl":"http://www.toei-anim.co.jp/movie/2010_precure_allstars/","watchers":366,"services":[],"otherServices":[],"hasBroadcastData":false,"broadcastStartDate":null,"broadcastWeekday":null,"broadcastTime":null,"creditNames":["朴璐美","松野太紀","川田妙子","仙台エリ","渕崎ゆり子","東堂いづみ","大塚隆史","村山功","平間由香","高梨康治、佐藤直紀","平澤晃弘","稲上晃、川村敏江、香川久、馬越嘉彦","青山充","大塚隆史、松本理恵","澤田豊二","末竹憲","映画プリキュアオールスターズ製作委員会(東映アニメーション、東映、バンダイ、アサツー・ディ・ケイ、朝日放送、マーベラスエンターテイメント、木下工務店)","東映アニメーション"],"castNames":["朴璐美","松野太紀","川田妙子","仙台エリ","渕崎ゆり子"],"media":"MOVIE"},{"id":239,"title":"裏切りは僕の名前を知っている","image":null,"officialSiteUrl":null,"watchers":360,"services":[],"otherServices":[],"hasBroadcastData":false,"broadcastStartDate":null,"broadcastWeekday":null,"broadcastTime":null,"creditNames":["子安武人","植田佳奈","井上麻里奈","岡本信彦","保志総一朗","桜美かつし","小田切ほたる","flyingDOG","西山茂","岩井和也","村永麻耶","海田庄吾","栫ヒロツグ","中山由美、松浦麻衣","J.C.STAFF","月刊Asuka(角川書店)","高橋ナツコ","「裏僕」製作委員会","明田川仁"],"castNames":["子安武人","植田佳奈","井上麻里奈","岡本信彦","保志総一朗"],"media":"TV"},{"id":908,"title":"ジュエルペット てぃんくる☆","image":null,"officialSiteUrl":"https://www.tv-tokyo.co.jp/contents/jewelpet2/index.html","watchers":341,"services":[],"otherServices":[],"hasBroadcastData":false,"broadcastStartDate":null,"broadcastWeekday":null,"broadcastTime":null,"creditNames":["高森奈津美","沢城みゆき","清水愛","片岡あづさ","ささきのぞみ","サンリオ、セガトイズ","山本天志","島田満","伊部由起子","宮川知子","春日礼児","津守裕子","鎌田克明、五十嵐慎一","中葉由美子、村井秀明","岩浪美和","浜口史郎","スタジオコメット","テレビ東京、テレビ東京メディアネット、ウィーヴ"],"castNames":["高森奈津美","沢城みゆき","清水愛","片岡あづさ","ささきのぞみ"],"media":"TV"},{"id":3627,"title":"劇場版 ブレイク ブレイド 第一章「覚醒ノ刻」","image":null,"officialSiteUrl":null,"watchers":304,"services":[],"otherServices":[],"hasBroadcastData":false,"broadcastStartDate":null,"broadcastWeekday":null,"broadcastTime":null,"creditNames":["林和良","花澤香菜","保志総一朗","神谷浩史","中村悠一","平野義久","柳瀬敬之","松村拓哉","小濱俊裕","関本美津子","船倉一晃","矢野さとし","鶴岡陽太","伊藤潤一","XEBEC","アミノテツロ","羽原信義","十川誠志","吉永裕ノ介","乗田拓茂"],"castNames":["林和良","花澤香菜","保志総一朗","神谷浩史","中村悠一"],"media":"MOVIE"},{"id":2409,"title":"RAINBOW 二舎六房の七人","image":"https://www.ntv.co.jp/rainbow/images/og_image.jpg","officialSiteUrl":"https://www.ntv.co.jp/rainbow/","watchers":304,"services":[],"otherServices":[],"hasBroadcastData":false,"broadcastStartDate":null,"broadcastWeekday":null,"broadcastTime":null,"creditNames":["安部譲二","柿崎正澄","神志那弘志","高屋敷英夫","菊池愛","高橋美香","清水友幸","増元由紀大","堀川佳典","寺内聡","三間雅文","倉橋静男","テクノサウンド","マッドハウス"],"castNames":[],"media":"TV"},{"id":810,"title":"さらい屋 五葉","image":null,"officialSiteUrl":null,"watchers":299,"services":[],"otherServices":[],"hasBroadcastData":false,"broadcastStartDate":null,"broadcastWeekday":null,"broadcastTime":null,"creditNames":["浪川大輔","大浦冬華","高塚正也","高梁碧","宝亀克寿","山田和弘","長坂智樹","一瀬美代子","常木志伸","望月智充","小西香葉、近藤由紀夫(MOKA☆)","山下喜光","中澤一登","オノ･ナツメ(月刊IKKI)","渡辺三千恵","佐藤正浩","マングローブ"],"castNames":["浪川大輔","大浦冬華","高塚正也","高梁碧","宝亀克寿"],"media":"TV"},{"id":3144,"title":"いばらの王 ‐King of Thorn‐","image":null,"officialSiteUrl":"http://www.kingofthorn.net/jp/","watchers":288,"services":[],"otherServices":[],"hasBroadcastData":false,"broadcastStartDate":null,"broadcastWeekday":null,"broadcastTime":null,"creditNames":["サンライズ"],"castNames":[],"media":"MOVIE"},{"id":1752,"title":"HEROMAN","image":null,"officialSiteUrl":null,"watchers":283,"services":[],"otherServices":[],"hasBroadcastData":false,"broadcastStartDate":null,"broadcastWeekday":null,"broadcastTime":null,"creditNames":["チョー","石塚運昇","木村良平","小幡真裕","小松未可子","木村俊也","岩沢れい子","近藤由美子","武半慎吾","原口昇","大和屋暁","難波日登志","スタン・リー","ボンズ","コヤマシゲト","川元利浩","富岡隆司"],"castNames":["チョー","石塚運昇","木村良平","小幡真裕","小松未可子"],"media":"TV"},{"id":11305,"title":"ONE PIECE FILM STRONG WORLD EPISODE:0","image":null,"officialSiteUrl":null,"watchers":255,"services":[],"otherServices":[],"hasBroadcastData":false,"broadcastStartDate":null,"broadcastWeekday":null,"broadcastTime":null,"creditNames":[],"castNames":[],"media":"OVA"},{"id":5916,"title":"GA 芸術科アートデザインクラス OVA「青空が描きたい」","image":null,"officialSiteUrl":"http://mv.avex.jp/ga/","watchers":248,"services":[],"otherServices":[],"hasBroadcastData":false,"broadcastStartDate":null,"broadcastWeekday":null,"broadcastTime":null,"creditNames":["AIC PLUS+"],"castNames":[],"media":"OVA"},{"id":3475,"title":"TRIGUN -Badlands Rumble-","image":null,"officialSiteUrl":null,"watchers":243,"services":[],"otherServices":[],"hasBroadcastData":false,"broadcastStartDate":null,"broadcastWeekday":null,"broadcastTime":null,"creditNames":["マッドハウス"],"castNames":[],"media":"MOVIE"},{"id":3230,"title":"劇場版 銀幕ヘタリア Axis Powers Paint it. White (白くぬれ！)","image":null,"officialSiteUrl":"http://hetalia.com/movie/index.htm","watchers":243,"services":[],"otherServices":[],"hasBroadcastData":false,"broadcastStartDate":null,"broadcastWeekday":null,"broadcastTime":null,"creditNames":["スタジオディーン"],"castNames":[],"media":"MOVIE"},{"id":1614,"title":"はなかっぱ","image":"http://www.hanakappa.jp/img/c_main.jpg","officialSiteUrl":"http://www.hanakappa.jp/index.html","watchers":192,"services":[],"otherServices":[],"hasBroadcastData":true,"broadcastStartDate":null,"broadcastWeekday":null,"broadcastTime":null,"creditNames":["植田佳奈","中川里江","緒方賢一","堀越真己","木内秀信","スタジオイゼナ、スタジオCJ、スタジオコメット、亜細亜堂、スタジオCJT","小山慎","神南スタジオ","あきやまただし","笠松美樹","藤山房伸","松宮由美","林一哉","やすみ哲夫","やすみ哲夫、山下友弘","のなかかずみ","グループ・タック","XEBEC","はなかっぱプロジェクト(東宝、メディアファクトリー、電通、グループ・タック、小学館、ソニーPCL、ギャガ)","SIGNAL.MD"],"castNames":["植田佳奈","中川里江","緒方賢一","堀越真己","木内秀信"],"media":"TV"},{"id":5875,"title":"劇場版 ブレイク ブレイド 第二章「訣別ノ路」","image":null,"officialSiteUrl":null,"watchers":191,"services":[],"otherServices":[],"hasBroadcastData":false,"broadcastStartDate":null,"broadcastWeekday":null,"broadcastTime":null,"creditNames":[],"castNames":[],"media":"MOVIE"},{"id":5025,"title":"のだめカンタービレ「特別番外編」","image":null,"officialSiteUrl":"http://gentei.kodansha.co.jp/content/nodame/index.html","watchers":165,"services":[],"otherServices":[],"hasBroadcastData":false,"broadcastStartDate":null,"broadcastWeekday":null,"broadcastTime":null,"creditNames":["伊藤静","下野紘","川澄綾子","折笠富美子","関智一","横谷昌宏","島村秀一","都築裕佳子","広橋真弓","大河内喜夫","西山茂","J.C.STAFF","明田川仁","小林七郎","今千秋"],"castNames":["伊藤静","下野紘","川澄綾子","折笠富美子","関智一"],"media":"OVA"},{"id":1773,"title":"ひめチェン！おとぎちっくアイドル リルぷりっ","image":null,"officialSiteUrl":null,"watchers":153,"services":[],"otherServices":[],"hasBroadcastData":false,"broadcastStartDate":null,"broadcastWeekday":null,"broadcastTime":null,"creditNames":["和田彩花(スマイレージ)","前田憂佳(スマイレージ)","福田花音(スマイレージ)","高木礼子","中司ゆう花","小学館集英社プロダクション","仲田美歩","渡辺敦子","SSJ","菊田浩巳","新田博史、山子泰弘","山田由香","森脇真琴","トムス・エンタテインメント"],"castNames":["和田彩花(スマイレージ)","前田憂佳(スマイレージ)","福田花音(スマイレージ)","高木礼子","中司ゆう花"],"media":"TV"},{"id":3827,"title":"ゆとりちゃん","image":null,"officialSiteUrl":"http://yutori-chan.jp/","watchers":118,"services":[],"otherServices":[],"hasBroadcastData":false,"broadcastStartDate":null,"broadcastWeekday":null,"broadcastTime":null,"creditNames":["渡辺明乃","野中藍","花澤香菜","宮崎寛務","矢部雅史","西尾公伯","Dr.モロー","田中由土里、アクタス","川口敬一郎","浅川美也","ぱすてるデザイン","アクタス","POP"],"castNames":["渡辺明乃","野中藍","花澤香菜","宮崎寛務","矢部雅史"],"media":"WEB"},{"id":5029,"title":"メタルファイトベイブレード 爆","image":null,"officialSiteUrl":"http://www.tv-tokyo.co.jp/contents/mf-beyblade/","watchers":102,"services":[],"otherServices":[],"hasBroadcastData":false,"broadcastStartDate":null,"broadcastWeekday":null,"broadcastTime":null,"creditNames":["Synergy SP"],"castNames":[],"media":"TV"},{"id":259,"title":"SDガンダム三国伝 Brave Battle Warriors","image":null,"officialSiteUrl":null,"watchers":92,"services":[],"otherServices":[],"hasBroadcastData":false,"broadcastStartDate":null,"broadcastWeekday":null,"broadcastTime":null,"creditNames":["サンライズ"],"castNames":[],"media":"TV"},{"id":2639,"title":"今日、恋をはじめます","image":null,"officialSiteUrl":null,"watchers":85,"services":[],"otherServices":[],"hasBroadcastData":false,"broadcastStartDate":null,"broadcastWeekday":null,"broadcastTime":null,"creditNames":["J.C.STAFF"],"castNames":[],"media":"OVA"},{"id":6869,"title":"秘密結社 鷹の爪 THE MOVIE4 〜カスペルスキーを持つ男〜","image":null,"officialSiteUrl":"http://鷹の爪.jp/","watchers":81,"services":[],"otherServices":[],"hasBroadcastData":false,"broadcastStartDate":null,"broadcastWeekday":null,"broadcastTime":null,"creditNames":[],"castNames":[],"media":"OVA"},{"id":5383,"title":"Peeping Life The Perfect Emotion","image":null,"officialSiteUrl":null,"watchers":69,"services":[],"otherServices":[],"hasBroadcastData":false,"broadcastStartDate":null,"broadcastWeekday":null,"broadcastTime":null,"creditNames":[],"castNames":[],"media":"OVA"},{"id":10742,"title":"\"文学少女\" メモワール","image":null,"officialSiteUrl":null,"watchers":65,"services":[],"otherServices":[],"hasBroadcastData":false,"broadcastStartDate":null,"broadcastWeekday":null,"broadcastTime":null,"creditNames":["Production I.G"],"castNames":[],"media":"OVA"},{"id":9711,"title":"ザ・ペンギンズ from マダガスカル シーズン1","image":null,"officialSiteUrl":null,"watchers":63,"services":[],"otherServices":[],"hasBroadcastData":false,"broadcastStartDate":null,"broadcastWeekday":null,"broadcastTime":null,"creditNames":["ドリームワークス・アニメーション・テレビジョン","ニコロデオン・アニメーション・スタジオ"],"castNames":[],"media":"TV"},{"id":5616,"title":"スター・ウォーズ/クローン・ウォーズ (テレビシリーズ シーズン2)","image":null,"officialSiteUrl":null,"watchers":62,"services":[],"otherServices":[],"hasBroadcastData":false,"broadcastStartDate":null,"broadcastWeekday":null,"broadcastTime":null,"creditNames":["ルーカスフィルム・アニメーション","ルーカスフィルム","ポリゴン・ピクチュアズ"],"castNames":[],"media":"TV"},{"id":2707,"title":"恋する暴君","image":null,"officialSiteUrl":null,"watchers":61,"services":[],"otherServices":[],"hasBroadcastData":false,"broadcastStartDate":null,"broadcastWeekday":null,"broadcastTime":null,"creditNames":["プライムタイム"],"castNames":[],"media":"OVA"},{"id":8545,"title":"ヘタリア Axis Powers (第2期) 未配信エピソード「おれさまにっき そのに(仮)」","image":null,"officialSiteUrl":"http://hetalia.com/top.htm","watchers":61,"services":[],"otherServices":[],"hasBroadcastData":false,"broadcastStartDate":null,"broadcastWeekday":null,"broadcastTime":null,"creditNames":[],"castNames":[],"media":"OVA"},{"id":1443,"title":"トランスフォーマー アニメイテッド","image":null,"officialSiteUrl":null,"watchers":56,"services":[],"otherServices":[],"hasBroadcastData":false,"broadcastStartDate":null,"broadcastWeekday":null,"broadcastTime":null,"creditNames":["野島健児","藤原啓治","若本規夫","高橋広樹","岸尾だいすけ","菊池悟史、金秀賢","辺見真起子","岩浪美和","電通","井上俊次","亜細亜堂","アンサー・スタジオ","STUDIO4℃","テレビ愛知","タカラトミーエンタメディア","カートゥーン ネットワーク・スタジオ"],"castNames":["野島健児","藤原啓治","若本規夫","高橋広樹","岸尾だいすけ"],"media":"TV"},{"id":12863,"title":"ソ・ラ・ノ・ヲ・ト 番外編 第7.5話「饗宴・砦ノ戦争」","image":null,"officialSiteUrl":"http://www.sorawoto.com/","watchers":55,"services":[],"otherServices":[],"hasBroadcastData":false,"broadcastStartDate":null,"broadcastWeekday":null,"broadcastTime":null,"creditNames":[],"castNames":[],"media":"OVA"},{"id":5914,"title":"閃光のナイトレイド OVA","image":null,"officialSiteUrl":"http://www.1931.tv/","watchers":48,"services":[],"otherServices":[],"hasBroadcastData":false,"broadcastStartDate":null,"broadcastWeekday":null,"broadcastTime":null,"creditNames":[],"castNames":[],"media":"OVA"},{"id":13801,"title":"バカとテストと召喚獣 第1期 映像特典","image":null,"officialSiteUrl":null,"watchers":48,"services":[],"otherServices":[],"hasBroadcastData":false,"broadcastStartDate":null,"broadcastWeekday":null,"broadcastTime":null,"creditNames":[],"castNames":[],"media":"OVA"},{"id":3046,"title":"窓辺ななみのWindows 7でPC自作応援コマーシャルっ！！","image":null,"officialSiteUrl":null,"watchers":37,"services":[],"otherServices":[],"hasBroadcastData":false,"broadcastStartDate":null,"broadcastWeekday":null,"broadcastTime":null,"creditNames":[],"castNames":[],"media":"OVA"},{"id":9349,"title":"デュエル・マスターズ クロスショック","image":null,"officialSiteUrl":"https://www.tv-tokyo.co.jp/contents/duel_cross/","watchers":31,"services":[],"otherServices":[],"hasBroadcastData":false,"broadcastStartDate":null,"broadcastWeekday":null,"broadcastTime":null,"creditNames":["小学館ミュージック&デジタル エンタテイメント"],"castNames":[],"media":"TV"},{"id":3629,"title":"プランゼット","image":null,"officialSiteUrl":null,"watchers":26,"services":[],"otherServices":[],"hasBroadcastData":false,"broadcastStartDate":null,"broadcastWeekday":null,"broadcastTime":null,"creditNames":[],"castNames":[],"media":"MOVIE"},{"id":5387,"title":"Peeping Life プランゼットコラボムービー版","image":null,"officialSiteUrl":null,"watchers":25,"services":[],"otherServices":[],"hasBroadcastData":false,"broadcastStartDate":null,"broadcastWeekday":null,"broadcastTime":null,"creditNames":[],"castNames":[],"media":"OVA"},{"id":4753,"title":"思春期","image":null,"officialSiteUrl":"http://miyukifukuda.web.fc2.com/","watchers":22,"services":[],"otherServices":[],"hasBroadcastData":false,"broadcastStartDate":null,"broadcastWeekday":null,"broadcastTime":null,"creditNames":[],"castNames":[],"media":"WEB"},{"id":10534,"title":"ダグの特別な一日","image":null,"officialSiteUrl":null,"watchers":21,"services":[],"otherServices":[],"hasBroadcastData":false,"broadcastStartDate":null,"broadcastWeekday":null,"broadcastTime":null,"creditNames":["ピクサー・アニメーション・スタジオ"],"castNames":[],"media":"OVA"},{"id":16585,"title":"いちばんうしろの大魔王　OVAもひとつおまけの大魔王","image":null,"officialSiteUrl":"https://www.marv.jp/special/daimao/","watchers":21,"services":[],"otherServices":[],"hasBroadcastData":false,"broadcastStartDate":null,"broadcastWeekday":null,"broadcastTime":null,"creditNames":[],"castNames":[],"media":"OVA"},{"id":2367,"title":"リングにかけろ1 影道編","image":null,"officialSiteUrl":null,"watchers":20,"services":[],"otherServices":[],"hasBroadcastData":false,"broadcastStartDate":null,"broadcastWeekday":null,"broadcastTime":null,"creditNames":["森田成一","田中理恵","草尾毅","石川英郎","神谷浩史","小村敏明","板坂泰江","倉橋隆","岡田将介","岡田忠博、森下誠（集英社）","森山義秀","森下孝三","上田益","井上栄作","荒木伸吾、姫野美智、井上栄作","黒田洋介","車田正美","東映アニメーション"],"castNames":["森田成一","田中理恵","草尾毅","石川英郎","神谷浩史"],"media":"TV"},{"id":14149,"title":"11eyes 第13話「桃色幻夢譚 〜ró zsaszí n é jszaka」","image":null,"officialSiteUrl":null,"watchers":20,"services":[],"otherServices":[],"hasBroadcastData":false,"broadcastStartDate":null,"broadcastWeekday":null,"broadcastTime":null,"creditNames":[],"castNames":[],"media":"OVA"},{"id":11476,"title":"極上!!めちゃモテ委員長 セカンドコレクション","image":null,"officialSiteUrl":null,"watchers":20,"services":[],"otherServices":[],"hasBroadcastData":false,"broadcastStartDate":null,"broadcastWeekday":null,"broadcastTime":null,"creditNames":["小学館ミュージック&デジタル エンタテイメント"],"castNames":[],"media":"TV"},{"id":12116,"title":"こひつじのティミー","image":null,"officialSiteUrl":null,"watchers":20,"services":[],"otherServices":[],"hasBroadcastData":false,"broadcastStartDate":null,"broadcastWeekday":null,"broadcastTime":null,"creditNames":["アードマン・アニメーションズ"],"castNames":[],"media":"TV"},{"id":874,"title":"しまじろう ヘソカ","image":null,"officialSiteUrl":null,"watchers":19,"services":[],"otherServices":[],"hasBroadcastData":false,"broadcastStartDate":null,"broadcastWeekday":null,"broadcastTime":null,"creditNames":["スタジオサインポスト"],"castNames":[],"media":"TV"},{"id":9798,"title":"きかんしゃトーマス 伝説の英雄","image":null,"officialSiteUrl":"https://www.thomasandfriends.jp/","watchers":18,"services":[],"otherServices":[],"hasBroadcastData":false,"broadcastStartDate":null,"broadcastWeekday":null,"broadcastTime":null,"creditNames":[],"castNames":[],"media":"MOVIE"},{"id":11340,"title":"9 〜9番目の奇妙な人形〜","image":null,"officialSiteUrl":null,"watchers":17,"services":[],"otherServices":[],"hasBroadcastData":false,"broadcastStartDate":null,"broadcastWeekday":null,"broadcastTime":null,"creditNames":[],"castNames":[],"media":"MOVIE"},{"id":10471,"title":"ペンギンの問題Max","image":null,"officialSiteUrl":null,"watchers":16,"services":[],"otherServices":[],"hasBroadcastData":false,"broadcastStartDate":null,"broadcastWeekday":null,"broadcastTime":null,"creditNames":["小学館ミュージック&デジタル エンタテイメント"],"castNames":[],"media":"TV"},{"id":17496,"title":"迷い猫ネコネコ動画","image":null,"officialSiteUrl":null,"watchers":12,"services":[],"otherServices":[],"hasBroadcastData":false,"broadcastStartDate":null,"broadcastWeekday":null,"broadcastTime":null,"creditNames":["岡本信彦","伊藤かな恵","井口裕香","竹達彩奈","吉野裕行","AIC"],"castNames":["岡本信彦","伊藤かな恵","井口裕香","竹達彩奈","吉野裕行"],"media":"OVA"},{"id":7734,"title":"最強武将伝 三国演義","image":null,"officialSiteUrl":null,"watchers":11,"services":[],"otherServices":[],"hasBroadcastData":false,"broadcastStartDate":null,"broadcastWeekday":null,"broadcastTime":null,"creditNames":[],"castNames":[],"media":"TV"},{"id":4736,"title":"Melan & Chory メラン&コリー","image":null,"officialSiteUrl":null,"watchers":11,"services":[],"otherServices":[],"hasBroadcastData":false,"broadcastStartDate":null,"broadcastWeekday":null,"broadcastTime":null,"creditNames":[],"castNames":[],"media":"WEB"},{"id":4737,"title":"Visual Acuity Test 視力検査","image":null,"officialSiteUrl":null,"watchers":11,"services":[],"otherServices":[],"hasBroadcastData":false,"broadcastStartDate":null,"broadcastWeekday":null,"broadcastTime":null,"creditNames":[],"castNames":[],"media":"WEB"},{"id":4752,"title":"失恋","image":null,"officialSiteUrl":"http://miyukifukuda.web.fc2.com/","watchers":10,"services":[],"otherServices":[],"hasBroadcastData":false,"broadcastStartDate":null,"broadcastWeekday":null,"broadcastTime":null,"creditNames":[],"castNames":[],"media":"WEB"},{"id":14175,"title":"チーズスイートホーム チーとコッチ、出会う。","image":null,"officialSiteUrl":null,"watchers":10,"services":[],"otherServices":[],"hasBroadcastData":false,"broadcastStartDate":null,"broadcastWeekday":null,"broadcastTime":null,"creditNames":[],"castNames":[],"media":"OVA"},{"id":14559,"title":"ロボと少女（仮）","image":null,"officialSiteUrl":"https://roboshoujo.work/","watchers":10,"services":[],"otherServices":[],"hasBroadcastData":false,"broadcastStartDate":null,"broadcastWeekday":null,"broadcastTime":null,"creditNames":[],"castNames":[],"media":"WEB"},{"id":14418,"title":"六畳間の侵略者!? プロモーションムービー","image":null,"officialSiteUrl":null,"watchers":10,"services":[],"otherServices":[],"hasBroadcastData":false,"broadcastStartDate":null,"broadcastWeekday":null,"broadcastTime":null,"creditNames":[],"castNames":[],"media":"WEB"},{"id":3812,"title":"ハニー東京","image":null,"officialSiteUrl":null,"watchers":9,"services":[],"otherServices":[],"hasBroadcastData":false,"broadcastStartDate":null,"broadcastWeekday":null,"broadcastTime":null,"creditNames":[],"castNames":[],"media":"WEB"},{"id":9783,"title":"きかんしゃトーマス 第13シーズン","image":null,"officialSiteUrl":"https://www.thomasandfriends.jp/","watchers":9,"services":[],"otherServices":[],"hasBroadcastData":false,"broadcastStartDate":null,"broadcastWeekday":null,"broadcastTime":null,"creditNames":["ヒット・エンターテインメント"],"castNames":[],"media":"TV"},{"id":12512,"title":"キック ザ・びっくりボーイ","image":null,"officialSiteUrl":null,"watchers":8,"services":[],"otherServices":[],"hasBroadcastData":false,"broadcastStartDate":null,"broadcastWeekday":null,"broadcastTime":null,"creditNames":["ディズニー・テレビジョン・アニメーション","マーキュリー・フィルムワークス"],"castNames":[],"media":"TV"},{"id":17509,"title":"一騎当千 XTREME XECUTOR 〜ユメ六景〜","image":null,"officialSiteUrl":null,"watchers":7,"services":[],"otherServices":[],"hasBroadcastData":false,"broadcastStartDate":null,"broadcastWeekday":null,"broadcastTime":null,"creditNames":[],"castNames":[],"media":"OVA"},{"id":12187,"title":"ジュノー","image":null,"officialSiteUrl":null,"watchers":4,"services":[],"otherServices":[],"hasBroadcastData":false,"broadcastStartDate":null,"broadcastWeekday":null,"broadcastTime":null,"creditNames":["スタジオ雲雀"],"castNames":[],"media":"MOVIE"},{"id":16621,"title":"スーパーストリートファイターIV オリジナルアニメーション","image":null,"officialSiteUrl":null,"watchers":4,"services":[],"otherServices":[],"hasBroadcastData":false,"broadcastStartDate":null,"broadcastWeekday":null,"broadcastTime":null,"creditNames":[],"castNames":[],"media":"OVA"},{"id":15954,"title":"水木しげるの遠野物語","image":null,"officialSiteUrl":null,"watchers":4,"services":[],"otherServices":[],"hasBroadcastData":false,"broadcastStartDate":null,"broadcastWeekday":null,"broadcastTime":null,"creditNames":[],"castNames":[],"media":"MOVIE"},{"id":17411,"title":"家庭教師ヒットマンREBORN! ミスターリボックのちゃおちゃおインタビュー","image":null,"officialSiteUrl":null,"watchers":4,"services":[],"otherServices":[],"hasBroadcastData":false,"broadcastStartDate":null,"broadcastWeekday":null,"broadcastTime":null,"creditNames":[],"castNames":[],"media":"OVA"},{"id":14636,"title":"進め！ガチムチ3兄弟","image":null,"officialSiteUrl":null,"watchers":3,"services":[],"otherServices":[],"hasBroadcastData":false,"broadcastStartDate":null,"broadcastWeekday":null,"broadcastTime":null,"creditNames":[],"castNames":[],"media":"WEB"},{"id":16549,"title":"ケツ犬","image":null,"officialSiteUrl":"https://www.toei-anim.co.jp/sp/ketsuinu/index.html","watchers":3,"services":[],"otherServices":[],"hasBroadcastData":false,"broadcastStartDate":null,"broadcastWeekday":null,"broadcastTime":null,"creditNames":["東映アニメーション"],"castNames":[],"media":"TV"},{"id":11277,"title":"フューチュラマ シーズン6 パート1","image":null,"officialSiteUrl":null,"watchers":2,"services":[],"otherServices":[],"hasBroadcastData":false,"broadcastStartDate":null,"broadcastWeekday":null,"broadcastTime":null,"creditNames":["20th テレビジョン"],"castNames":[],"media":"TV"},{"id":16056,"title":"なんちゃって","image":null,"officialSiteUrl":null,"watchers":2,"services":[],"otherServices":[],"hasBroadcastData":false,"broadcastStartDate":null,"broadcastWeekday":null,"broadcastTime":null,"creditNames":["シンエイ動画"],"castNames":[],"media":"WEB"},{"id":16057,"title":"ポテッコベイビーズ","image":null,"officialSiteUrl":null,"watchers":2,"services":[],"otherServices":[],"hasBroadcastData":false,"broadcastStartDate":null,"broadcastWeekday":null,"broadcastTime":null,"creditNames":["シンエイ動画"],"castNames":[],"media":"WEB"},{"id":16770,"title":"ネイバーズ","image":null,"officialSiteUrl":null,"watchers":2,"services":[],"otherServices":[],"hasBroadcastData":false,"broadcastStartDate":null,"broadcastWeekday":null,"broadcastTime":null,"creditNames":[],"castNames":[],"media":"TV"}]}
